su6_plugin_demo/__about__.py
su6_plugin_demo/__init__.py
su6_plugin_demo/cli.py
su6_plugin_demo-0.3.0.dist-info/METADATA
su6_plugin_demo-0.3.0.dist-info/WHEEL
su6_plugin_demo-0.3.0.dist-info/entry_points.txt
su6_plugin_demo-0.3.0.dist-info/licenses/LICENSE.txt
su6_plugin_demo-0.3.0.dist-info/RECORD
