Metadata-Version: 2.1
Name: su6-plugin-demo
Version: 0.3.0
Summary: Demo plugin for su6-checker
Project-URL: Documentation, https://github.com/robinvandernoord/su6-plugin-demo#readme
Project-URL: Issues, https://github.com/robinvandernoord/su6-plugin-demo/issues
Project-URL: Source, https://github.com/robinvandernoord/su6-plugin-demo
Author-email: Robin van der Noord <robinvandernoord@gmail.com>
License-Expression: MIT
License-File: LICENSE.txt
Classifier: Development Status :: 4 - Beta
Classifier: Programming Language :: Python
Classifier: Programming Language :: Python :: 3.10
Classifier: Programming Language :: Python :: 3.11
Classifier: Programming Language :: Python :: 3.12
Classifier: Programming Language :: Python :: Implementation :: CPython
Classifier: Programming Language :: Python :: Implementation :: PyPy
Requires-Python: >=3.10
Requires-Dist: su6
Provides-Extra: dev
Requires-Dist: su6[all]; extra == 'dev'
